torchani/__init__.py
torchani/_core.py
torchani/_testing.py
torchani/_version.py
torchani/annotations.py
torchani/arch.py
torchani/ase.py
torchani/cli.py
torchani/constants.py
torchani/cutoffs.py
torchani/electro.py
torchani/grad.py
torchani/io.py
torchani/models.py
torchani/neighbors.py
torchani/neurochem.py
torchani/paths.py
torchani/sae.py
torchani/sae_estimation.py
torchani/transforms.py
torchani/tuples.py
torchani/units.py
torchani/utils.py
torchani/aev/__init__.py
torchani/aev/_computer.py
torchani/aev/_terms.py
torchani/csrc/CMakeLists.txt
torchani/csrc/README.md
torchani/csrc/__init__.py
torchani/csrc/aev.cu
torchani/csrc/aev.h
torchani/csrc/cell_list.cpp
torchani/csrc/cuaev.cpp
torchani/csrc/cuaev_cub.cuh
torchani/csrc/mnp.cpp
torchani/datasets/__init__.jinja
torchani/datasets/__init__.py
torchani/datasets/_utils.py
torchani/datasets/anidataset.py
torchani/datasets/batching.py
torchani/datasets/builtin.jinja
torchani/datasets/builtin.py
torchani/datasets/builtin_datasets.json
torchani/datasets/filters.py
torchani/datasets/md5s.csv
torchani/datasets/backends/__init__.py
torchani/datasets/backends/hdf5_impl.py
torchani/datasets/backends/interface.py
torchani/datasets/backends/parquet_impl.py
torchani/datasets/backends/public.py
torchani/datasets/backends/zarr_impl.py
torchani/legacy_data/__init__.py
torchani/legacy_data/_pyanitools.py
torchani/nn/__init__.py
torchani/nn/_containers.py
torchani/nn/_core.py
torchani/nn/_infer.py
torchani/nn/_internal.py
torchani/potentials/__init__.py
torchani/potentials/core.py
torchani/potentials/dftd3.py
torchani/potentials/fixed_coulomb.py
torchani/potentials/lj.py
torchani/potentials/nnp.py
torchani/potentials/utils.py
torchani/potentials/xtb.py
torchani/potentials/zbl.py
torchani/resources/README.md
torchani/resources/atomic_constants.json
torchani/resources/c6.h5
torchani/resources/functional_d3bj_constants.json
torchani-2.7.9.dist-info/licenses/LICENSE
torchani-2.7.9.dist-info/METADATA
torchani-2.7.9.dist-info/WHEEL
torchani-2.7.9.dist-info/entry_points.txt
torchani-2.7.9.dist-info/top_level.txt
torchani-2.7.9.dist-info/RECORD
