Metadata-Version: 2.4
Name: torchani
Version: 2.7.9
Summary: PyTorch implementation of the ANI neural network potential family
Author-email: Ignacio Pickering <ign.pickering@gmail.com>, Xiang Gao <qasdfgtyuiop@gmail.com>, Jinze Xue <jinzexue@chem.ufl.edu>
License-Expression: MIT
Project-URL: repository, https://github.com/aiqm/torchani
Keywords: machine-learning,neural-networks,deep-learning,chemistry,torch,energy
Requires-Python: >=3.9
License-File: LICENSE
Requires-Dist: torch<=2.8,>=2.0
Requires-Dist: numpy
Requires-Dist: typing_extensions>=4.0.0
Requires-Dist: h5py
Requires-Dist: tqdm
Requires-Dist: ninja
Requires-Dist: typer
Requires-Dist: rich
Requires-Dist: ase
Requires-Dist: pandas
Requires-Dist: pyarrow
Requires-Dist: zarr<3
Requires-Dist: huggingface_hub
Dynamic: license-file
